{
 "cells": [
  {
   "cell_type": "markdown",
   "id": "c1fe49b7",
   "metadata": {},
   "source": [
    "### Lists vs Tuples"
   ]
  },
  {
   "cell_type": "code",
   "execution_count": 1,
   "id": "10c4f549",
   "metadata": {},
   "outputs": [],
   "source": [
    "from dis import dis"
   ]
  },
  {
   "cell_type": "code",
   "execution_count": 2,
   "id": "85ee3ed0",
   "metadata": {},
   "outputs": [
    {
     "data": {
      "text/plain": [
       "(1, 2, 3)"
      ]
     },
     "execution_count": 2,
     "metadata": {},
     "output_type": "execute_result"
    }
   ],
   "source": [
    "(1, 2, 3)"
   ]
  },
  {
   "cell_type": "code",
   "execution_count": 3,
   "id": "9f169e5b",
   "metadata": {},
   "outputs": [
    {
     "data": {
      "text/plain": [
       "[1, 2, 3]"
      ]
     },
     "execution_count": 3,
     "metadata": {},
     "output_type": "execute_result"
    }
   ],
   "source": [
    "[1, 2, 3]"
   ]
  },
  {
   "cell_type": "code",
   "execution_count": 4,
   "id": "14545e0f",
   "metadata": {},
   "outputs": [
    {
     "name": "stdout",
     "output_type": "stream",
     "text": [
      "  0           0 RESUME                   0\n",
      "\n",
      "  1           2 RETURN_CONST             0 ((1, 2, 3, 'a'))\n"
     ]
    }
   ],
   "source": [
    "dis(compile('(1, 2, 3, \"a\")', 'string', 'eval'))"
   ]
  },
  {
   "cell_type": "code",
   "execution_count": 5,
   "id": "7dd9f97d",
   "metadata": {},
   "outputs": [
    {
     "name": "stdout",
     "output_type": "stream",
     "text": [
      "  0           0 RESUME                   0\n",
      "\n",
      "  1           2 BUILD_LIST               0\n",
      "              4 LOAD_CONST               0 ((1, 2, 3, 'a'))\n",
      "              6 LIST_EXTEND              1\n",
      "              8 RETURN_VALUE\n"
     ]
    }
   ],
   "source": [
    "dis(compile('[1, 2, 3, \"a\"]', 'string', 'eval'))"
   ]
  },
  {
   "cell_type": "code",
   "execution_count": 6,
   "id": "8f5cd9ea",
   "metadata": {},
   "outputs": [
    {
     "name": "stdout",
     "output_type": "stream",
     "text": [
      "  0           0 RESUME                   0\n",
      "\n",
      "  1           2 LOAD_CONST               0 (1)\n",
      "              4 LOAD_CONST               1 (2)\n",
      "              6 LOAD_CONST               2 (3)\n",
      "              8 LOAD_CONST               3 (10)\n",
      "             10 LOAD_CONST               4 (20)\n",
      "             12 BUILD_LIST               2\n",
      "             14 BUILD_LIST               4\n",
      "             16 RETURN_VALUE\n"
     ]
    }
   ],
   "source": [
    "dis(compile('[1, 2, 3, [10, 20]]', 'string', 'eval'))"
   ]
  },
  {
   "cell_type": "code",
   "execution_count": 7,
   "id": "1d4e5e1e",
   "metadata": {},
   "outputs": [
    {
     "data": {
      "text/plain": [
       "0.1591016260000515"
      ]
     },
     "execution_count": 7,
     "metadata": {},
     "output_type": "execute_result"
    }
   ],
   "source": [
    "from timeit import timeit\n",
    "timeit(\"(1, 2, 3, 4, 5, 6, 7, 8, 9)\", number=10_000_000)"
   ]
  },
  {
   "cell_type": "code",
   "execution_count": 8,
   "id": "534c953a",
   "metadata": {},
   "outputs": [
    {
     "data": {
      "text/plain": [
       "1.0321791750000102"
      ]
     },
     "execution_count": 8,
     "metadata": {},
     "output_type": "execute_result"
    }
   ],
   "source": [
    "timeit(\"[1, 2, 3, 4, 5, 6, 7, 8, 9]\", number=10_000_000)"
   ]
  },
  {
   "cell_type": "code",
   "execution_count": 9,
   "id": "5a712a02",
   "metadata": {},
   "outputs": [],
   "source": [
    "def fn1():\n",
    "    pass"
   ]
  },
  {
   "cell_type": "code",
   "execution_count": 10,
   "id": "0072896d",
   "metadata": {},
   "outputs": [
    {
     "name": "stdout",
     "output_type": "stream",
     "text": [
      "  0           0 RESUME                   0\n",
      "\n",
      "  1           2 LOAD_NAME                0 (fn1)\n",
      "              4 LOAD_CONST               0 (10)\n",
      "              6 LOAD_CONST               1 (20)\n",
      "              8 BUILD_TUPLE              3\n",
      "             10 RETURN_VALUE\n"
     ]
    }
   ],
   "source": [
    "dis(compile('(fn1, 10, 20)', 'string', 'eval'))"
   ]
  },
  {
   "cell_type": "code",
   "execution_count": 11,
   "id": "76eef1db",
   "metadata": {},
   "outputs": [
    {
     "name": "stdout",
     "output_type": "stream",
     "text": [
      "  0           0 RESUME                   0\n",
      "\n",
      "  1           2 LOAD_CONST               0 (1)\n",
      "              4 LOAD_CONST               1 (2)\n",
      "              6 LOAD_CONST               2 (3)\n",
      "              8 LOAD_CONST               3 (10)\n",
      "             10 LOAD_CONST               4 (20)\n",
      "             12 BUILD_LIST               2\n",
      "             14 BUILD_TUPLE              4\n",
      "             16 RETURN_VALUE\n"
     ]
    }
   ],
   "source": [
    "dis(compile('(1, 2, 3, [10, 20])', 'string', 'eval'))"
   ]
  },
  {
   "cell_type": "code",
   "execution_count": 12,
   "id": "5f883d7f",
   "metadata": {},
   "outputs": [
    {
     "data": {
      "text/plain": [
       "1.8219288660000075"
      ]
     },
     "execution_count": 12,
     "metadata": {},
     "output_type": "execute_result"
    }
   ],
   "source": [
    "timeit(\"([1,2], 10, 20)\", number=10_000_000)"
   ]
  },
  {
   "cell_type": "code",
   "execution_count": 13,
   "id": "7b21024a",
   "metadata": {},
   "outputs": [
    {
     "data": {
      "text/plain": [
       "2.31544711000015"
      ]
     },
     "execution_count": 13,
     "metadata": {},
     "output_type": "execute_result"
    }
   ],
   "source": [
    "timeit(\"[[1,2], 10, 20]\", number=10_000_000)"
   ]
  },
  {
   "cell_type": "code",
   "execution_count": 14,
   "id": "fce13ca0",
   "metadata": {},
   "outputs": [],
   "source": [
    "l1 = [1, 2, 3, 4, 5, 6, 7, 8, 9]\n",
    "t1 = (1, 2, 3, 4, 5, 6, 7, 8, 9)"
   ]
  },
  {
   "cell_type": "code",
   "execution_count": 15,
   "id": "b9ce1951",
   "metadata": {},
   "outputs": [
    {
     "data": {
      "text/plain": [
       "(140131166056512, 140131166091200)"
      ]
     },
     "execution_count": 15,
     "metadata": {},
     "output_type": "execute_result"
    }
   ],
   "source": [
    "l2 = list(l1)\n",
    "id(l1), id(l2)"
   ]
  },
  {
   "cell_type": "code",
   "execution_count": 16,
   "id": "173a571b",
   "metadata": {},
   "outputs": [],
   "source": [
    "t2 = tuple(t1)"
   ]
  },
  {
   "cell_type": "code",
   "execution_count": 17,
   "id": "715180f8",
   "metadata": {},
   "outputs": [
    {
     "data": {
      "text/plain": [
       "(140131175932736, 140131175932736)"
      ]
     },
     "execution_count": 17,
     "metadata": {},
     "output_type": "execute_result"
    }
   ],
   "source": [
    "id(t1), id(t2)"
   ]
  },
  {
   "cell_type": "code",
   "execution_count": 18,
   "id": "5f034301",
   "metadata": {},
   "outputs": [
    {
     "data": {
      "text/plain": [
       "0.26500972400003775"
      ]
     },
     "execution_count": 18,
     "metadata": {},
     "output_type": "execute_result"
    }
   ],
   "source": [
    "timeit('tuple((1, 2, 3, 4, 5))', number=5_000_000)"
   ]
  },
  {
   "cell_type": "code",
   "execution_count": 19,
   "id": "3186ab92",
   "metadata": {},
   "outputs": [
    {
     "data": {
      "text/plain": [
       "0.9926621300000988"
      ]
     },
     "execution_count": 19,
     "metadata": {},
     "output_type": "execute_result"
    }
   ],
   "source": [
    "timeit('list((1, 2, 3, 4, 5))', number=5_000_000)"
   ]
  },
  {
   "cell_type": "code",
   "execution_count": 1,
   "id": "579177f2",
   "metadata": {},
   "outputs": [
    {
     "name": "stdout",
     "output_type": "stream",
     "text": [
      "1 items: 48, delta=8\n",
      "2 items: 56, delta=8\n",
      "3 items: 64, delta=8\n",
      "4 items: 72, delta=8\n",
      "5 items: 80, delta=8\n",
      "6 items: 88, delta=8\n",
      "7 items: 96, delta=8\n",
      "8 items: 104, delta=8\n",
      "9 items: 112, delta=8\n",
      "10 items: 120, delta=8\n"
     ]
    }
   ],
   "source": [
    "import sys\n",
    "\n",
    "t = tuple()\n",
    "prev = sys.getsizeof(t)\n",
    "for i in range(10):\n",
    "    c = tuple(range(i+1))\n",
    "    size_c = sys.getsizeof(c)\n",
    "    delta, prev = size_c - prev, size_c\n",
    "    print(f'{i+1} items: {size_c}, delta={delta}')"
   ]
  },
  {
   "cell_type": "code",
   "execution_count": 2,
   "id": "f1f0f592",
   "metadata": {},
   "outputs": [
    {
     "name": "stdout",
     "output_type": "stream",
     "text": [
      "1 items: 72, delta=16\n",
      "2 items: 72, delta=0\n",
      "3 items: 88, delta=16\n",
      "4 items: 88, delta=0\n",
      "5 items: 104, delta=16\n",
      "6 items: 104, delta=0\n",
      "7 items: 120, delta=16\n",
      "8 items: 120, delta=0\n",
      "9 items: 136, delta=16\n",
      "10 items: 136, delta=0\n"
     ]
    }
   ],
   "source": [
    "l = list()\n",
    "prev = sys.getsizeof(l)\n",
    "for i in range(10):\n",
    "    c = list(range(i+1))\n",
    "    size_c = sys.getsizeof(c)\n",
    "    delta, prev = size_c - prev, size_c\n",
    "    print(f'{i+1} items: {size_c}, delta={delta}')"
   ]
  },
  {
   "cell_type": "code",
   "execution_count": null,
   "id": "c224363e",
   "metadata": {},
   "outputs": [],
   "source": []
  }
 ],
 "metadata": {
  "kernelspec": {
   "display_name": "Python (venv)",
   "language": "python",
   "name": "venv"
  },
  "language_info": {
   "codemirror_mode": {
    "name": "ipython",
    "version": 3
   },
   "file_extension": ".py",
   "mimetype": "text/x-python",
   "name": "python",
   "nbconvert_exporter": "python",
   "pygments_lexer": "ipython3",
   "version": "3.12.3"
  }
 },
 "nbformat": 4,
 "nbformat_minor": 5
}
