{
 "cells": [
  {
   "cell_type": "markdown",
   "id": "599c2991",
   "metadata": {},
   "source": [
    "### Generator Expressions"
   ]
  },
  {
   "cell_type": "code",
   "execution_count": 1,
   "id": "5fb5a9cd",
   "metadata": {},
   "outputs": [],
   "source": [
    "l = [i**2 for i in range(5)]"
   ]
  },
  {
   "cell_type": "code",
   "execution_count": 2,
   "id": "4db214b8",
   "metadata": {},
   "outputs": [
    {
     "data": {
      "text/plain": [
       "[0, 1, 4, 9, 16]"
      ]
     },
     "execution_count": 2,
     "metadata": {},
     "output_type": "execute_result"
    }
   ],
   "source": [
    "l"
   ]
  },
  {
   "cell_type": "code",
   "execution_count": 3,
   "id": "e500efba",
   "metadata": {},
   "outputs": [],
   "source": [
    "g = (i**2 for i in range(5))"
   ]
  },
  {
   "cell_type": "code",
   "execution_count": 4,
   "id": "d3f4d5df",
   "metadata": {},
   "outputs": [
    {
     "data": {
      "text/plain": [
       "generator"
      ]
     },
     "execution_count": 4,
     "metadata": {},
     "output_type": "execute_result"
    }
   ],
   "source": [
    "type(g)"
   ]
  },
  {
   "cell_type": "code",
   "execution_count": 5,
   "id": "427cb212",
   "metadata": {},
   "outputs": [
    {
     "name": "stdout",
     "output_type": "stream",
     "text": [
      "0\n",
      "1\n",
      "4\n",
      "9\n",
      "16\n"
     ]
    }
   ],
   "source": [
    "for item in g:\n",
    "    print(item)"
   ]
  },
  {
   "cell_type": "code",
   "execution_count": 6,
   "id": "008f8520",
   "metadata": {},
   "outputs": [
    {
     "data": {
      "text/plain": [
       "[]"
      ]
     },
     "execution_count": 6,
     "metadata": {},
     "output_type": "execute_result"
    }
   ],
   "source": [
    "list(g)"
   ]
  },
  {
   "cell_type": "code",
   "execution_count": 7,
   "id": "bab3ea4a",
   "metadata": {},
   "outputs": [],
   "source": [
    "import dis"
   ]
  },
  {
   "cell_type": "code",
   "execution_count": 9,
   "id": "6ef5eba9",
   "metadata": {},
   "outputs": [],
   "source": [
    "exp = compile('[i**2 for i in range(5)]',\n",
    "              filename='<string>', mode='eval')"
   ]
  },
  {
   "cell_type": "code",
   "execution_count": 10,
   "id": "bc95fa11",
   "metadata": {},
   "outputs": [
    {
     "name": "stdout",
     "output_type": "stream",
     "text": [
      "  0           0 RESUME                   0\n",
      "\n",
      "  1           2 PUSH_NULL\n",
      "              4 LOAD_NAME                0 (range)\n",
      "              6 LOAD_CONST               0 (5)\n",
      "              8 CALL                     1\n",
      "             16 GET_ITER\n",
      "             18 LOAD_FAST_AND_CLEAR      0 (i)\n",
      "             20 SWAP                     2\n",
      "             22 BUILD_LIST               0\n",
      "             24 SWAP                     2\n",
      "        >>   26 FOR_ITER                 7 (to 44)\n",
      "             30 STORE_FAST               0 (i)\n",
      "             32 LOAD_FAST                0 (i)\n",
      "             34 LOAD_CONST               1 (2)\n",
      "             36 BINARY_OP                8 (**)\n",
      "             40 LIST_APPEND              2\n",
      "             42 JUMP_BACKWARD            9 (to 26)\n",
      "        >>   44 END_FOR\n",
      "             46 SWAP                     2\n",
      "             48 STORE_FAST               0 (i)\n",
      "             50 RETURN_VALUE\n",
      "        >>   52 SWAP                     2\n",
      "             54 POP_TOP\n",
      "             56 SWAP                     2\n",
      "             58 STORE_FAST               0 (i)\n",
      "             60 RERAISE                  0\n",
      "ExceptionTable:\n",
      "  22 to 44 -> 52 [2]\n"
     ]
    }
   ],
   "source": [
    "dis.dis(exp)"
   ]
  },
  {
   "cell_type": "code",
   "execution_count": 11,
   "id": "ba062a92",
   "metadata": {},
   "outputs": [],
   "source": [
    "exp = compile('(i**2 for i in range(5))',\n",
    "              filename='<string>', mode='eval')"
   ]
  },
  {
   "cell_type": "code",
   "execution_count": 12,
   "id": "67541936",
   "metadata": {},
   "outputs": [
    {
     "name": "stdout",
     "output_type": "stream",
     "text": [
      "  0           0 RESUME                   0\n",
      "\n",
      "  1           2 LOAD_CONST               0 (<code object <genexpr> at 0x7f2285fe9020, file \"<string>\", line 1>)\n",
      "              4 MAKE_FUNCTION            0\n",
      "              6 PUSH_NULL\n",
      "              8 LOAD_NAME                0 (range)\n",
      "             10 LOAD_CONST               1 (5)\n",
      "             12 CALL                     1\n",
      "             20 GET_ITER\n",
      "             22 CALL                     0\n",
      "             30 RETURN_VALUE\n",
      "\n",
      "Disassembly of <code object <genexpr> at 0x7f2285fe9020, file \"<string>\", line 1>:\n",
      "  1           0 RETURN_GENERATOR\n",
      "              2 POP_TOP\n",
      "              4 RESUME                   0\n",
      "              6 LOAD_FAST                0 (.0)\n",
      "        >>    8 FOR_ITER                 9 (to 30)\n",
      "             12 STORE_FAST               1 (i)\n",
      "             14 LOAD_FAST                1 (i)\n",
      "             16 LOAD_CONST               0 (2)\n",
      "             18 BINARY_OP                8 (**)\n",
      "             22 YIELD_VALUE              1\n",
      "             24 RESUME                   1\n",
      "             26 POP_TOP\n",
      "             28 JUMP_BACKWARD           11 (to 8)\n",
      "        >>   30 END_FOR\n",
      "             32 RETURN_CONST             1 (None)\n",
      "        >>   34 CALL_INTRINSIC_1         3 (INTRINSIC_STOPITERATION_ERROR)\n",
      "             36 RERAISE                  1\n",
      "ExceptionTable:\n",
      "  4 to 32 -> 34 [0] lasti\n"
     ]
    }
   ],
   "source": [
    "dis.dis(exp)"
   ]
  },
  {
   "cell_type": "code",
   "execution_count": null,
   "id": "fe9c3389",
   "metadata": {},
   "outputs": [],
   "source": []
  }
 ],
 "metadata": {
  "kernelspec": {
   "display_name": "Python (venv)",
   "language": "python",
   "name": "venv"
  },
  "language_info": {
   "codemirror_mode": {
    "name": "ipython",
    "version": 3
   },
   "file_extension": ".py",
   "mimetype": "text/x-python",
   "name": "python",
   "nbconvert_exporter": "python",
   "pygments_lexer": "ipython3",
   "version": "3.12.3"
  }
 },
 "nbformat": 4,
 "nbformat_minor": 5
}
